aivmlib/__init__.py
aivmlib/__main__.py
aivmlib/schemas/aivm_manifest.py
aivmlib/schemas/aivm_manifest_constants.py
aivmlib/schemas/style_bert_vits2.py
aivmlib/utils.py
aivmlib-1.2.2.dist-info/METADATA
aivmlib-1.2.2.dist-info/WHEEL
aivmlib-1.2.2.dist-info/entry_points.txt
aivmlib-1.2.2.dist-info/licenses/LICENSE
aivmlib-1.2.2.dist-info/RECORD
