Metadata-Version: 2.4
Name: aivmlib
Version: 1.2.2
Summary: Aivis Voice Model File (.aivm/.aivmx) Utility Library
License: MIT
License-File: LICENSE
Author: Aivis Project
Author-email: contact@aivis-project.com
Requires-Python: >=3.10,<4.0
Classifier: License :: OSI Approved :: MIT License
Classifier: Programming Language :: Python :: 3
Classifier: Programming Language :: Python :: 3.10
Classifier: Programming Language :: Python :: 3.11
Classifier: Programming Language :: Python :: 3.12
Classifier: Programming Language :: Python :: 3.13
Classifier: Programming Language :: Python :: 3.14
Requires-Dist: onnx (>=1.17.0)
Requires-Dist: pydantic (>=2.4.0)
Requires-Dist: typer (>=0.12.1)
Project-URL: Documentation, https://github.com/Aivis-Project/aivmlib
Project-URL: Homepage, https://github.com/Aivis-Project/aivmlib
Project-URL: Repository, https://github.com/Aivis-Project/aivmlib
